{
	"location": {
		"country": "Germany",
		"city": "Heilbronn"
	},
	"portal": {
		"url": "https://www.buga2019.de/de/Veranstaltungen/Kalender.php",
		"title": "BUGA-Kalender",
		"description": "",
		"license": "",
		"licenseURL": "",
		"attribution": "",
		"author": "",
		"created": "",
		"updated": ""
	},
	"front": {
		"textTop": "Noch",
		"textBottom": "bis zur BUGA-Eröffnung",
		"value": "2019-04-17",
		"unit": "",
		"changePerDay": "",
		"format": "date",
		"background": "img/buga.svg",
		"color": "#ffffff"
	},
	"back": {
		"text": "Auf der BUGA finden viele Veranstaltungen statt. Diese können im Kalender gefunden werden.",
		"color": "#000000",
		"cssClass": ""
	}
}
